asphalt/web/__init__.py
asphalt/web/aiohttp.py
asphalt/web/asgi3.py
asphalt/web/django.py
asphalt/web/fastapi.py
asphalt/web/litestar.py
asphalt/web/py.typed
asphalt/web/starlette.py
asphalt_web-1.3.1.dist-info/LICENSE
asphalt_web-1.3.1.dist-info/METADATA
asphalt_web-1.3.1.dist-info/WHEEL
asphalt_web-1.3.1.dist-info/entry_points.txt
asphalt_web-1.3.1.dist-info/top_level.txt
asphalt_web-1.3.1.dist-info/RECORD
