Metadata-Version: 2.1
Name: asphalt-web
Version: 1.3.1
Summary: Web framework integrations for the Asphalt framework
Author-email: Alex Grönholm <alex.gronholm@nextday.fi>
License: Apache License 2.0
Project-URL: Documentation, https://asphalt-web.readthedocs.org/en/latest/
Project-URL: Source code, https://github.com/asphalt-framework/asphalt-web
Project-URL: Issue tracker, https://github.com/asphalt-framework/asphalt-web/issues
Project-URL: Help and support, https://github.com/asphalt-framework/asphalt/wiki/Help-and-support
Classifier: Development Status :: 5 - Production/Stable
Classifier: Intended Audience :: Developers
Classifier: License :: OSI Approved :: Apache Software License
Classifier: Topic :: Software Development :: Libraries :: Application Frameworks
Classifier: Environment :: Web Environment
Classifier: Framework :: AsyncIO
Classifier: Typing :: Typed
Classifier: Programming Language :: Python
Classifier: Programming Language :: Python :: 3 :: Only
Classifier: Programming Language :: Python :: 3.8
Classifier: Programming Language :: Python :: 3.9
Classifier: Programming Language :: Python :: 3.10
Classifier: Programming Language :: Python :: 3.11
Classifier: Programming Language :: Python :: 3.12
Requires-Python: >=3.8
License-File: LICENSE
Requires-Dist: asphalt ~=4.8
Provides-Extra: aiohttp
Requires-Dist: aiohttp >=3.8 ; extra == 'aiohttp'
Provides-Extra: asgi3
Requires-Dist: asgiref ~=3.5 ; extra == 'asgi3'
Requires-Dist: uvicorn >=0.17.6 ; extra == 'asgi3'
Provides-Extra: django
Requires-Dist: asgiref ~=3.5 ; extra == 'django'
Requires-Dist: Django >=3.2 ; extra == 'django'
Requires-Dist: uvicorn >=0.17.6 ; extra == 'django'
Provides-Extra: doc
Requires-Dist: Sphinx >=7.0 ; extra == 'doc'
Requires-Dist: sphinx-rtd-theme >=1.3.0 ; extra == 'doc'
Requires-Dist: sphinx-autodoc-typehints >=1.22 ; extra == 'doc'
Requires-Dist: sphinx-tabs >=3.3.1 ; extra == 'doc'
Requires-Dist: asphalt-web[aiohttp,asgi3,django,fastapi,litestar,starlette] ; extra == 'doc'
Provides-Extra: fastapi
Requires-Dist: asgiref ~=3.5 ; extra == 'fastapi'
Requires-Dist: fastapi >=0.75 ; extra == 'fastapi'
Requires-Dist: uvicorn >=0.17.6 ; extra == 'fastapi'
Provides-Extra: litestar
Requires-Dist: asgiref ~=3.5 ; extra == 'litestar'
Requires-Dist: litestar >=2.2 ; extra == 'litestar'
Requires-Dist: uvicorn >=0.17.6 ; extra == 'litestar'
Provides-Extra: starlette
Requires-Dist: asgiref ~=3.5 ; extra == 'starlette'
Requires-Dist: starlette >=0.17 ; extra == 'starlette'
Requires-Dist: uvicorn >=0.17.6 ; extra == 'starlette'
Provides-Extra: test
Requires-Dist: pytest ; extra == 'test'
Requires-Dist: pytest-asyncio ; extra == 'test'
Requires-Dist: httpx ; extra == 'test'
Requires-Dist: websockets ; extra == 'test'
Requires-Dist: asphalt-web[asgi3,fastapi,starlette] ; extra == 'test'
Requires-Dist: Django >=3.2 ; (platform_python_implementation == "CPython") and extra == 'test'
Requires-Dist: litestar >=2.2 ; (platform_python_implementation == "CPython") and extra == 'test'
Requires-Dist: aiohttp >=3.8 ; (python_version < "3.12") and extra == 'test'
